calibrated/__init__.py
calibrated-0.0.1.dist-info/LICENSE
calibrated-0.0.1.dist-info/METADATA
calibrated-0.0.1.dist-info/WHEEL
calibrated-0.0.1.dist-info/top_level.txt
calibrated-0.0.1.dist-info/RECORD
