Metadata-Version: 2.1
Name: calibrated
Version: 0.0.1
Summary: This middleware gives same structure in django success and error case.
Home-page: https://github.com/anshul217/calibrated
Author: Anshul Gupta
Author-email: anshulgupta217@gmail.com
License: UNKNOWN
Platform: UNKNOWN
Classifier: Programming Language :: Python :: 3
Classifier: License :: OSI Approved :: MIT License
Classifier: Operating System :: OS Independent
Requires-Python: >=3.6
